ssl_certinfo/__init__.py
ssl_certinfo/__main__.py
ssl_certinfo/cli.py
ssl_certinfo/ssl_certinfo.py
ssl_certinfo/validation.py
ssl_certinfo-1.1.2.dist-info/entry_points.txt
ssl_certinfo-1.1.2.dist-info/LICENSE
ssl_certinfo-1.1.2.dist-info/WHEEL
ssl_certinfo-1.1.2.dist-info/METADATA
ssl_certinfo-1.1.2.dist-info/RECORD
