Metadata-Version: 2.1
Name: ssl-certinfo
Version: 1.1.2
Summary: SSL CertInfo displays expiration dates and other information for SSL certificates from a set of hosts.
Home-page: https://github.com/stdtom/ssl_certinfo
License: Apache Software License 2.0
Author: StdTom
Author-email: stdtom@gmx.net
Requires-Python: >=3.8,<4.0
Classifier: Development Status :: 4 - Beta
Classifier: Intended Audience :: Information Technology
Classifier: License :: OSI Approved :: Apache Software License
Classifier: License :: Other/Proprietary License
Classifier: Natural Language :: English
Classifier: Programming Language :: Python :: 3
Classifier: Programming Language :: Python :: 3.10
Classifier: Programming Language :: Python :: 3.8
Classifier: Programming Language :: Python :: 3.9
Requires-Dist: PyYAML
Requires-Dist: pandas
Requires-Dist: pyOpenSSL
Requires-Dist: tabulate
Requires-Dist: tqdm
Project-URL: Repository, https://github.com/stdtom/ssl_certinfo
